backplate_auth/__init__.py
backplate_auth/decorator.py
backplate_auth/endpoint.py
backplate_auth/exceptions.py
backplate_auth/flow.py
backplate_auth/helpers.py
backplate_auth/jwt.py
backplate_auth/sessions.py
backplate_auth-0.3.0.dist-info/DESCRIPTION.rst
backplate_auth-0.3.0.dist-info/METADATA
backplate_auth-0.3.0.dist-info/RECORD
backplate_auth-0.3.0.dist-info/WHEEL
backplate_auth-0.3.0.dist-info/metadata.json
backplate_auth-0.3.0.dist-info/top_level.txt
