Metadata-Version: 2.0
Name: backplate-auth
Version: 0.3.0
Summary: RESTful API Auth Helpers
Home-page: https://github.com/studioarmix/backplate-auth
Author: Peter Boyer
Author-email: petertboyer@gmail.com
License: MIT
Platform: UNKNOWN
Requires-Dist: flask
Requires-Dist: flask-restful
Requires-Dist: pyjwt
Requires-Dist: webargs
